Workbook

Sheet Transactions
A1: Date | B1: Category | C1: Description | D1: Amount | E1: Type | F1: Month | G1: Payment Mode | H1: Merchant/App | I1: Notes
A2: 2026-05-01 | B2: Salary | C2: Monthly Salary | D2: 50000 | E2: Income | F2: =TEXT(A2,"MMM-YYYY") -> May-2026
A3: 2026-05-02 | B3: Rent | C3: House Rent | D3: 12000 | E3: Expense | F3: =TEXT(A3,"MMM-YYYY") -> May-2026
A4: 2026-05-03 | B4: EMI | C4: Bike EMI | D4: 5000 | E4: Expense | F4: =TEXT(A4,"MMM-YYYY") -> May-2026
A5: 2026-05-04 | B5: Electricity | C5: Electricity Bill | D5: 1500 | E5: Expense | F5: =TEXT(A5,"MMM-YYYY") -> May-2026
A6: 2026-05-05 | B6: SIP | C6: Mutual Fund SIP | D6: 8000 | E6: Investment | F6: =TEXT(A6,"MMM-YYYY") -> May-2026
F7: =TEXT(A7,"MMM-YYYY") -> Jan-1900
F8: =TEXT(A8,"MMM-YYYY") -> Jan-1900
F9: =TEXT(A9,"MMM-YYYY") -> Jan-1900
A10: 2026-06-02 | B10: UPI Expenditure | C10: GPay Grocery | D10: 1200 | E10: Expense | F10: =TEXT(A10,"MMM-YYYY") -> Jun-2026 | G10: UPI | H10: Google Pay | I10: Daily groceries
A11: 2026-06-03 | B11: Medicine Purchase | C11: Medical Store | D11: 800 | E11: Expense | F11: =TEXT(A11,"MMM-YYYY") -> Jun-2026 | G11: Card | H11: Apollo | I11: Cold medicine
A12: 2026-06-05 | B12: Ecommerce Purchase | C12: Amazon order | D12: 2500 | E12: Expense | F12: =TEXT(A12,"MMM-YYYY") -> Jun-2026 | G12: UPI | H12: Amazon | I12: Headphones
A13: 2026-06-06 | B13: Kitchen/Eatery Purchase | C13: Vegetables | D13: 700 | E13: Expense | F13: =TEXT(A13,"MMM-YYYY") -> Jun-2026 | G13: Cash | H13: Local Market | I13: Weekly vegetables

Sheet Monthly Summary
A1: Month | B1: Income | C1: Expense | D1: Investment | E1: Savings | F1: Overspending Alert
A2: May-2026 | B2: =SUMIFS(Transactions!D:D,Transactions!F:F,A2,Transactions!E:E,"Income") -> 50000 | C2: =SUMIFS(Transactions!D:D,Transactions!F:F,A2,Transactions!E:E,"Expense") -> 18500 | D2: =SUMIFS(Transactions!D:D,Transactions!F:F,A2,Transactions!E:E,"Investment") -> 8000 | E2: =B2-C2-D2 -> 23500 | F2: =IF(C2>B2*0.7,"⚠ High Spending","✅ Safe") -> ✅ Safe
A3: Jun-2026 | B3: =SUMIFS(Transactions!D:D,Transactions!F:F,A3,Transactions!E:E,"Income") -> 0 | C3: =SUMIFS(Transactions!D:D,Transactions!F:F,A3,Transactions!E:E,"Expense") -> 5200 | D3: =SUMIFS(Transactions!D:D,Transactions!F:F,A3,Transactions!E:E,"Investment") -> 0 | E3: =B3-C3-D3 -> -5200 | F3: =IF(C3>B3*0.7,"⚠ High Spending","✅ Safe") -> ⚠ High Spending
A4: Jul-2026 | B4: =SUMIFS(Transactions!D:D,Transactions!F:F,A4,Transactions!E:E,"Income") -> 0 | C4: =SUMIFS(Transactions!D:D,Transactions!F:F,A4,Transactions!E:E,"Expense") -> 0 | D4: =SUMIFS(Transactions!D:D,Transactions!F:F,A4,Transactions!E:E,"Investment") -> 0 | E4: =B4-C4-D4 -> 0 | F4: =IF(C4>B4*0.7,"⚠ High Spending","✅ Safe") -> ✅ Safe
A5: Aug-2026 | B5: =SUMIFS(Transactions!D:D,Transactions!F:F,A5,Transactions!E:E,"Income") -> 0 | C5: =SUMIFS(Transactions!D:D,Transactions!F:F,A5,Transactions!E:E,"Expense") -> 0 | D5: =SUMIFS(Transactions!D:D,Transactions!F:F,A5,Transactions!E:E,"Investment") -> 0 | E5: =B5-C5-D5 -> 0 | F5: =IF(C5>B5*0.7,"⚠ High Spending","✅ Safe") -> ✅ Safe

Sheet Dashboard
A1: Personal Finance Dashboard
A3: Total Income | B3: =SUM('Monthly Summary'!B:B) -> 50000
A5: Total Expense | B5: =SUM('Monthly Summary'!C:C) -> 23700
A7: Total Investment | B7: =SUM('Monthly Summary'!D:D) -> 8000
A9: Net Savings | B9: =SUM('Monthly Summary'!E:E) -> 18300

Sheet Expense Analysis
A1: Category | B1: Total
A2: Rent | B2: =SUMIFS(Transactions!D:D,Transactions!B:B,"Rent") -> 12000
A3: EMI | B3: =SUMIFS(Transactions!D:D,Transactions!B:B,"EMI") -> 5000
A4: Electricity | B4: =SUMIFS(Transactions!D:D,Transactions!B:B,"Electricity") -> 1500
A5: Food | B5: =SUMIFS(Transactions!D:D,Transactions!B:B,"Food") -> 0

Sheet Monthwise Analysis
A1: Month | B1: Total Expense | C1: UPI | D1: Medicine | E1: Food | F1: Ecommerce | G1: Kitchen/Eatery | H1: Investment | I1: Savings
A2: May-2026 | B2: =SUMIFS(Transactions!D:D,Transactions!F:F,A2,Transactions!E:E,"Expense") -> 18500 | C2: =SUMIFS(Transactions!D:D,Transactions!F:F,A2,Transactions!B:B,"UPI Expenditure") -> 0 | D2: =SUMIFS(Transactions!D:D,Transactions!F:F,A2,Transactions!B:B,"Medicine Purchase") -> 0 | E2: =SUMIFS(Transactions!D:D,Transactions!F:F,A2,Transactions!B:B,"Food Purchase") -> 0 | F2: =SUMIFS(Transactions!D:D,Transactions!F:F,A2,Transactions!B:B,"Ecommerce Purchase") -> 0 | G2: =SUMIFS(Transactions!D:D,Transactions!F:F,A2,Transactions!B:B,"Kitchen/Eatery Purchase") -> 0 | H2: =SUMIFS(Transactions!D:D,Transactions!F:F,A2,Transactions!E:E,"Investment") -> 8000 | I2: =SUMIFS(Transactions!D:D,Transactions!F:F,A2,Transactions!E:E,"Income")-B2-H2 -> 23500
A3: Jun-2026 | B3: =SUMIFS(Transactions!D:D,Transactions!F:F,A3,Transactions!E:E,"Expense") -> 5200 | C3: =SUMIFS(Transactions!D:D,Transactions!F:F,A3,Transactions!B:B,"UPI Expenditure") -> 1200 | D3: =SUMIFS(Transactions!D:D,Transactions!F:F,A3,Transactions!B:B,"Medicine Purchase") -> 800 | E3: =SUMIFS(Transactions!D:D,Transactions!F:F,A3,Transactions!B:B,"Food Purchase") -> 0 | F3: =SUMIFS(Transactions!D:D,Transactions!F:F,A3,Transactions!B:B,"Ecommerce Purchase") -> 2500 | G3: =SUMIFS(Transactions!D:D,Transactions!F:F,A3,Transactions!B:B,"Kitchen/Eatery Purchase") -> 700 | H3: =SUMIFS(Transactions!D:D,Transactions!F:F,A3,Transactions!E:E,"Investment") -> 0 | I3: =SUMIFS(Transactions!D:D,Transactions!F:F,A3,Transactions!E:E,"Income")-B3-H3 -> -5200
A4: Jul-2026 | B4: =SUMIFS(Transactions!D:D,Transactions!F:F,A4,Transactions!E:E,"Expense") -> 0 | C4: =SUMIFS(Transactions!D:D,Transactions!F:F,A4,Transactions!B:B,"UPI Expenditure") -> 0 | D4: =SUMIFS(Transactions!D:D,Transactions!F:F,A4,Transactions!B:B,"Medicine Purchase") -> 0 | E4: =SUMIFS(Transactions!D:D,Transactions!F:F,A4,Transactions!B:B,"Food Purchase") -> 0 | F4: =SUMIFS(Transactions!D:D,Transactions!F:F,A4,Transactions!B:B,"Ecommerce Purchase") -> 0 | G4: =SUMIFS(Transactions!D:D,Transactions!F:F,A4,Transactions!B:B,"Kitchen/Eatery Purchase") -> 0 | H4: =SUMIFS(Transactions!D:D,Transactions!F:F,A4,Transactions!E:E,"Investment") -> 0 | I4: =SUMIFS(Transactions!D:D,Transactions!F:F,A4,Transactions!E:E,"Income")-B4-H4 -> 0
A5: Aug-2026 | B5: =SUMIFS(Transactions!D:D,Transactions!F:F,A5,Transactions!E:E,"Expense") -> 0 | C5: =SUMIFS(Transactions!D:D,Transactions!F:F,A5,Transactions!B:B,"UPI Expenditure") -> 0 | D5: =SUMIFS(Transactions!D:D,Transactions!F:F,A5,Transactions!B:B,"Medicine Purchase") -> 0 | E5: =SUMIFS(Transactions!D:D,Transactions!F:F,A5,Transactions!B:B,"Food Purchase") -> 0 | F5: =SUMIFS(Transactions!D:D,Transactions!F:F,A5,Transactions!B:B,"Ecommerce Purchase") -> 0 | G5: =SUMIFS(Transactions!D:D,Transactions!F:F,A5,Transactions!B:B,"Kitchen/Eatery Purchase") -> 0 | H5: =SUMIFS(Transactions!D:D,Transactions!F:F,A5,Transactions!E:E,"Investment") -> 0 | I5: =SUMIFS(Transactions!D:D,Transactions!F:F,A5,Transactions!E:E,"Income")-B5-H5 -> 0
A6: Sep-2026 | B6: =SUMIFS(Transactions!D:D,Transactions!F:F,A6,Transactions!E:E,"Expense") -> 0 | C6: =SUMIFS(Transactions!D:D,Transactions!F:F,A6,Transactions!B:B,"UPI Expenditure") -> 0 | D6: =SUMIFS(Transactions!D:D,Transactions!F:F,A6,Transactions!B:B,"Medicine Purchase") -> 0 | E6: =SUMIFS(Transactions!D:D,Transactions!F:F,A6,Transactions!B:B,"Food Purchase") -> 0 | F6: =SUMIFS(Transactions!D:D,Transactions!F:F,A6,Transactions!B:B,"Ecommerce Purchase") -> 0 | G6: =SUMIFS(Transactions!D:D,Transactions!F:F,A6,Transactions!B:B,"Kitchen/Eatery Purchase") -> 0 | H6: =SUMIFS(Transactions!D:D,Transactions!F:F,A6,Transactions!E:E,"Investment") -> 0 | I6: =SUMIFS(Transactions!D:D,Transactions!F:F,A6,Transactions!E:E,"Income")-B6-H6 -> 0
A7: Oct-2026 | B7: =SUMIFS(Transactions!D:D,Transactions!F:F,A7,Transactions!E:E,"Expense") -> 0 | C7: =SUMIFS(Transactions!D:D,Transactions!F:F,A7,Transactions!B:B,"UPI Expenditure") -> 0 | D7: =SUMIFS(Transactions!D:D,Transactions!F:F,A7,Transactions!B:B,"Medicine Purchase") -> 0 | E7: =SUMIFS(Transactions!D:D,Transactions!F:F,A7,Transactions!B:B,"Food Purchase") -> 0 | F7: =SUMIFS(Transactions!D:D,Transactions!F:F,A7,Transactions!B:B,"Ecommerce Purchase") -> 0 | G7: =SUMIFS(Transactions!D:D,Transactions!F:F,A7,Transactions!B:B,"Kitchen/Eatery Purchase") -> 0 | H7: =SUMIFS(Transactions!D:D,Transactions!F:F,A7,Transactions!E:E,"Investment") -> 0 | I7: =SUMIFS(Transactions!D:D,Transactions!F:F,A7,Transactions!E:E,"Income")-B7-H7 -> 0
A8: Nov-2026 | B8: =SUMIFS(Transactions!D:D,Transactions!F:F,A8,Transactions!E:E,"Expense") -> 0 | C8: =SUMIFS(Transactions!D:D,Transactions!F:F,A8,Transactions!B:B,"UPI Expenditure") -> 0 | D8: =SUMIFS(Transactions!D:D,Transactions!F:F,A8,Transactions!B:B,"Medicine Purchase") -> 0 | E8: =SUMIFS(Transactions!D:D,Transactions!F:F,A8,Transactions!B:B,"Food Purchase") -> 0 | F8: =SUMIFS(Transactions!D:D,Transactions!F:F,A8,Transactions!B:B,"Ecommerce Purchase") -> 0 | G8: =SUMIFS(Transactions!D:D,Transactions!F:F,A8,Transactions!B:B,"Kitchen/Eatery Purchase") -> 0 | H8: =SUMIFS(Transactions!D:D,Transactions!F:F,A8,Transactions!E:E,"Investment") -> 0 | I8: =SUMIFS(Transactions!D:D,Transactions!F:F,A8,Transactions!E:E,"Income")-B8-H8 -> 0
A9: Dec-2026 | B9: =SUMIFS(Transactions!D:D,Transactions!F:F,A9,Transactions!E:E,"Expense") -> 0 | C9: =SUMIFS(Transactions!D:D,Transactions!F:F,A9,Transactions!B:B,"UPI Expenditure") -> 0 | D9: =SUMIFS(Transactions!D:D,Transactions!F:F,A9,Transactions!B:B,"Medicine Purchase") -> 0 | E9: =SUMIFS(Transactions!D:D,Transactions!F:F,A9,Transactions!B:B,"Food Purchase") -> 0 | F9: =SUMIFS(Transactions!D:D,Transactions!F:F,A9,Transactions!B:B,"Ecommerce Purchase") -> 0 | G9: =SUMIFS(Transactions!D:D,Transactions!F:F,A9,Transactions!B:B,"Kitchen/Eatery Purchase") -> 0 | H9: =SUMIFS(Transactions!D:D,Transactions!F:F,A9,Transactions!E:E,"Investment") -> 0 | I9: =SUMIFS(Transactions!D:D,Transactions!F:F,A9,Transactions!E:E,"Income")-B9-H9 -> 0

Sheet Yearly Analysis
A1: Year | B1: Total Income | C1: Total Expense | D1: Total Investment | E1: Total Savings | F1: Net Worth | G1: Financial Status
A2: 2026 | B2: =SUMPRODUCT((YEAR(Transactions!A2:A1000)=A2)*(Transactions!E2:E1000="Income")*(Transactions!D2:D1000)) -> 50000 | C2: =SUMPRODUCT((YEAR(Transactions!A2:A1000)=A2)*(Transactions!E2:E1000="Expense")*(Transactions!D2:D1000)) -> 23700 | D2: =SUMPRODUCT((YEAR(Transactions!A2:A1000)=A2)*(Transactions!E2:E1000="Investment")*(Transactions!D2:D1000)) -> 8000 | E2: =B2-C2-D2 -> 18300 | F2: =E2+D2 -> 26300 | G2: =IF(E2>0,"✅ Positive Savings","⚠ Low Savings") -> ✅ Positive Savings
A3: 2027 | B3: =SUMPRODUCT((YEAR(Transactions!A2:A1000)=A3)*(Transactions!E2:E1000="Income")*(Transactions!D2:D1000)) -> 0 | C3: =SUMPRODUCT((YEAR(Transactions!A2:A1000)=A3)*(Transactions!E2:E1000="Expense")*(Transactions!D2:D1000)) -> 0 | D3: =SUMPRODUCT((YEAR(Transactions!A2:A1000)=A3)*(Transactions!E2:E1000="Investment")*(Transactions!D2:D1000)) -> 0 | E3: =B3-C3-D3 -> 0 | F3: =E3+D3 -> 0 | G3: =IF(E3>0,"✅ Positive Savings","⚠ Low Savings") -> ⚠ Low Savings
A4: 2028 | B4: =SUMPRODUCT((YEAR(Transactions!A2:A1000)=A4)*(Transactions!E2:E1000="Income")*(Transactions!D2:D1000)) -> 0 | C4: =SUMPRODUCT((YEAR(Transactions!A2:A1000)=A4)*(Transactions!E2:E1000="Expense")*(Transactions!D2:D1000)) -> 0 | D4: =SUMPRODUCT((YEAR(Transactions!A2:A1000)=A4)*(Transactions!E2:E1000="Investment")*(Transactions!D2:D1000)) -> 0 | E4: =B4-C4-D4 -> 0 | F4: =E4+D4 -> 0 | G4: =IF(E4>0,"✅ Positive Savings","⚠ Low Savings") -> ⚠ Low Savings
A5: 2029 | B5: =SUMPRODUCT((YEAR(Transactions!A2:A1000)=A5)*(Transactions!E2:E1000="Income")*(Transactions!D2:D1000)) -> 0 | C5: =SUMPRODUCT((YEAR(Transactions!A2:A1000)=A5)*(Transactions!E2:E1000="Expense")*(Transactions!D2:D1000)) -> 0 | D5: =SUMPRODUCT((YEAR(Transactions!A2:A1000)=A5)*(Transactions!E2:E1000="Investment")*(Transactions!D2:D1000)) -> 0 | E5: =B5-C5-D5 -> 0 | F5: =E5+D5 -> 0 | G5: =IF(E5>0,"✅ Positive Savings","⚠ Low Savings") -> ⚠ Low Savings
A6: 2030 | B6: =SUMPRODUCT((YEAR(Transactions!A2:A1000)=A6)*(Transactions!E2:E1000="Income")*(Transactions!D2:D1000)) -> 0 | C6: =SUMPRODUCT((YEAR(Transactions!A2:A1000)=A6)*(Transactions!E2:E1000="Expense")*(Transactions!D2:D1000)) -> 0 | D6: =SUMPRODUCT((YEAR(Transactions!A2:A1000)=A6)*(Transactions!E2:E1000="Investment")*(Transactions!D2:D1000)) -> 0 | E6: =B6-C6-D6 -> 0 | F6: =E6+D6 -> 0 | G6: =IF(E6>0,"✅ Positive Savings","⚠ Low Savings") -> ⚠ Low Savings
